pinkfish777/__init__.py
pinkfish777/analysis.py
pinkfish777/benchmark.py
pinkfish777/fetch.py
pinkfish777/indicator.py
pinkfish777/itable.py
pinkfish777/pfcalendar.py
pinkfish777/pfstatistics.py
pinkfish777/plot.py
pinkfish777/portfolio.py
pinkfish777/stock_market_calendar.py
pinkfish777/trade.py
pinkfish777/utility.py
pinkfish777-0.1.6.dist-info/METADATA
pinkfish777-0.1.6.dist-info/WHEEL
pinkfish777-0.1.6.dist-info/licenses/LICENSE
pinkfish777-0.1.6.dist-info/RECORD
