Metadata-Version: 2.4
Name: pinkfish777
Version: 0.1.6
Summary: Add your description here
License-File: LICENSE
Requires-Python: >=3.13
Requires-Dist: from-root>=1.3.0
Requires-Dist: matplotlib>=3.10.8
Requires-Dist: pandas>=2.3.3
Requires-Dist: seaborn>=0.13.2
Requires-Dist: yfinance>=0.2.66
